[
  {
    "id": "01",
    "title": "The Complete JavaScript Course 2022",
    "lesson": "14",
    "students": 66,
    "duration": "18h 20m",
    "image": "./images/1.jpg",
    "price": "$90.00"
  },
  {
    "id": "02",
    "title": "Complete WordPress Course 2022",
    "lesson": "11",
    "students": 36,
    "duration": "7h 30m",
    "image": "./images/2.jpg",
    "price": "$18.00"
  },
  {
    "id": "03",
    "title": "Complete Financial Analyst Advance Course",
    "lesson": "11",
    "students": 87,
    "duration": "15h 30m",
    "image": "./images/3.jpg",
    "price": "$14.00"
  },
  {
    "id": "04",
    "title": "Build Your Perfect Diet Meal Plan",
    "lesson": "07",
    "students": 10,
    "duration": "4h 30m",
    "image": "./images/4.jpg",
    "price": "$25.00"
  },
  {
    "id": "05",
    "title": "PHP Beginners – Become a PHP Master",
    "lesson": "27",
    "students": 98,
    "duration": "22h 30m",
    "image": "./images/5.jpg",
    "price": "$21.00"
  },
  {
    "id": "06",
    "title": "Complete Financial Analyst Advance Course",
    "lesson": "19",
    "students": 47,
    "duration": "17h 30m",
    "image": "./images/6.jpg",
    "price": "$16.00"
  },
  {
    "id": "07",
    "title": "Sales Training: Practical Sales Techniques",
    "lesson": "14",
    "students": 66,
    "duration": "10h 9m",
    "image": "./images/7.jpg",
    "price": "$13.00"
  },
  {
    "id": "08",
    "title": "Sales Training: Practical Advance Techniques",
    "lesson": "04",
    "students": 48,
    "duration": "14h 9m",
    "image": "./images/8.jpg",
    "price": "$25.00"
  },
  {
    "id": "09",
    "title": "User Experience Design Course 2022",
    "lesson": "8",
    "students": 34,
    "duration": "10h 49m",
    "image": "./images/9.jpg",
    "price": "$33.00"
  }
]
